{
  "additionalFiles": "../..",
  "builtInLibrariesFolders": "/home/mirko/.arduino15/libraries",
  "compiler.optimization_flags": "-Os",
  "customBuildProperties": "",
  "fqbn": "esp32:esp32:jczn_2432s028r:UploadSpeed=115200,CPUFreq=240,FlashFreq=80,FlashMode=qio,FlashSize=4M,PartitionScheme=huge_app,DebugLevel=verbose,LoopCore=1,EventsCore=0,EraseFlash=none,JTAGAdapter=default,ZigbeeMode=default",
  "hardwareFolders": "/home/mirko/.arduino15/packages",
  "otherLibrariesFolders": "/home/mirko/Arduino/libraries",
  "sketchLocation": "/home/mirko/Arduino/ESP32_CYD_Meteo_station"
}